oxiboy/__init__.py
oxiboy/app.py
oxiboy/migrations/README
oxiboy/migrations/alembic.ini
oxiboy/migrations/env.py
oxiboy/migrations/script.py.mako
oxiboy/migrations/versions/ec938bba34d4_initial_migration.py
oxiboy-0.1.0.dist-info/METADATA
oxiboy-0.1.0.dist-info/WHEEL
oxiboy-0.1.0.dist-info/RECORD
